<?xml version="1.0" encoding="utf-8"?>
<ArrayOfTask xmlns:xsi="http://www.w3.org/2001/XMLSchema-instance" xmlns:xsd="http://www.w3.org/2001/XMLSchema">
  <Task>
    <Id>1</Id>
    <Alias>digging</Alias>
    <Description>the engineeer need to take control over the digging so we can start build</Description>
    <CreatedAtDate>2023-12-11T19:54:32.5827116+02:00</CreatedAtDate>
    <IsMileStone>false</IsMileStone>
    <isActive>true</isActive>
    <ScheduledDate xsi:nil="true" />
    <StartDate xsi:nil="true" />
    <RequiredEffortTime xsi:nil="true" />
    <DeadlineDate xsi:nil="true" />
    <CompleteDate xsi:nil="true" />
    <EngineerId xsi:nil="true" />
    <Complexity xsi:nil="true" />
  </Task>
  <Task>
    <Id>2</Id>
    <Alias>foundations</Alias>
    <Description>the engineeer need to take control over the foundation proccess</Description>
    <CreatedAtDate>2023-11-17T19:54:33.5464215+02:00</CreatedAtDate>
    <IsMileStone>false</IsMileStone>
    <isActive>true</isActive>
    <ScheduledDate xsi:nil="true" />
    <StartDate xsi:nil="true" />
    <RequiredEffortTime xsi:nil="true" />
    <DeadlineDate xsi:nil="true" />
    <CompleteDate xsi:nil="true" />
    <EngineerId xsi:nil="true" />
    <Complexity xsi:nil="true" />
  </Task>
  <Task>
    <Id>3</Id>
    <Alias>cement</Alias>
    <Description>the engineeer need to take controll over the creation of the cement</Description>
    <CreatedAtDate>2023-12-23T19:54:33.5648586+02:00</CreatedAtDate>
    <IsMileStone>false</IsMileStone>
    <isActive>true</isActive>
    <ScheduledDate xsi:nil="true" />
    <StartDate xsi:nil="true" />
    <RequiredEffortTime xsi:nil="true" />
    <DeadlineDate xsi:nil="true" />
    <CompleteDate xsi:nil="true" />
    <EngineerId xsi:nil="true" />
    <Complexity xsi:nil="true" />
  </Task>
  <Task>
    <Id>4</Id>
    <Alias>iron</Alias>
    <Description>the engineeer need to take control over the iron for the structure</Description>
    <CreatedAtDate>2023-12-03T19:54:33.5851188+02:00</CreatedAtDate>
    <IsMileStone>false</IsMileStone>
    <isActive>true</isActive>
    <ScheduledDate xsi:nil="true" />
    <StartDate xsi:nil="true" />
    <RequiredEffortTime xsi:nil="true" />
    <DeadlineDate xsi:nil="true" />
    <CompleteDate xsi:nil="true" />
    <EngineerId xsi:nil="true" />
    <Complexity xsi:nil="true" />
  </Task>
  <Task>
    <Id>5</Id>
    <Alias>brick</Alias>
    <Description>the engineeer need to take control over the import of the bricks</Description>
    <CreatedAtDate>2023-11-03T19:54:33.6051662+02:00</CreatedAtDate>
    <IsMileStone>false</IsMileStone>
    <isActive>true</isActive>
    <ScheduledDate xsi:nil="true" />
    <StartDate xsi:nil="true" />
    <RequiredEffortTime xsi:nil="true" />
    <DeadlineDate xsi:nil="true" />
    <CompleteDate xsi:nil="true" />
    <EngineerId xsi:nil="true" />
    <Complexity xsi:nil="true" />
  </Task>
  <Task>
    <Id>6</Id>
    <Alias>protective measures</Alias>
    <Description>the engineeer need to take control over the buying of the protective measures</Description>
    <CreatedAtDate>2023-11-24T19:54:33.6283004+02:00</CreatedAtDate>
    <IsMileStone>false</IsMileStone>
    <isActive>true</isActive>
    <ScheduledDate xsi:nil="true" />
    <StartDate xsi:nil="true" />
    <RequiredEffortTime xsi:nil="true" />
    <DeadlineDate xsi:nil="true" />
    <CompleteDate xsi:nil="true" />
    <EngineerId xsi:nil="true" />
    <Complexity xsi:nil="true" />
  </Task>
  <Task>
    <Id>7</Id>
    <Alias>ladder</Alias>
    <Description>the engineeer need to take control over buildig the ladder for the house</Description>
    <CreatedAtDate>2023-12-06T19:54:33.6502941+02:00</CreatedAtDate>
    <IsMileStone>false</IsMileStone>
    <isActive>true</isActive>
    <ScheduledDate xsi:nil="true" />
    <StartDate xsi:nil="true" />
    <RequiredEffortTime xsi:nil="true" />
    <DeadlineDate xsi:nil="true" />
    <CompleteDate xsi:nil="true" />
    <EngineerId xsi:nil="true" />
    <Complexity xsi:nil="true" />
  </Task>
  <Task>
    <Id>8</Id>
    <Alias>cranes</Alias>
    <Description>the engineeer need to take control moving the cranes</Description>
    <CreatedAtDate>2023-11-23T19:54:33.6687366+02:00</CreatedAtDate>
    <IsMileStone>false</IsMileStone>
    <isActive>true</isActive>
    <ScheduledDate xsi:nil="true" />
    <StartDate xsi:nil="true" />
    <RequiredEffortTime xsi:nil="true" />
    <DeadlineDate xsi:nil="true" />
    <CompleteDate xsi:nil="true" />
    <EngineerId xsi:nil="true" />
    <Complexity xsi:nil="true" />
  </Task>
  <Task>
    <Id>9</Id>
    <Alias>paint</Alias>
    <Description>the engineeer need to take control over painting the house</Description>
    <CreatedAtDate>2023-12-07T19:54:33.6854285+02:00</CreatedAtDate>
    <IsMileStone>false</IsMileStone>
    <isActive>true</isActive>
    <ScheduledDate xsi:nil="true" />
    <StartDate xsi:nil="true" />
    <RequiredEffortTime xsi:nil="true" />
    <DeadlineDate xsi:nil="true" />
    <CompleteDate xsi:nil="true" />
    <EngineerId xsi:nil="true" />
    <Complexity xsi:nil="true" />
  </Task>
  <Task>
    <Id>10</Id>
    <Alias>electricity</Alias>
    <Description>the engineeer need to take control over the electric wires and the wiring</Description>
    <CreatedAtDate>2023-12-04T19:54:33.7045547+02:00</CreatedAtDate>
    <IsMileStone>false</IsMileStone>
    <isActive>true</isActive>
    <ScheduledDate xsi:nil="true" />
    <StartDate xsi:nil="true" />
    <RequiredEffortTime xsi:nil="true" />
    <DeadlineDate xsi:nil="true" />
    <CompleteDate xsi:nil="true" />
    <EngineerId xsi:nil="true" />
    <Complexity xsi:nil="true" />
  </Task>
  <Task>
    <Id>11</Id>
    <Alias>plumbing</Alias>
    <Description>the engineeer need to take control over the plumbing</Description>
    <CreatedAtDate>2023-11-09T19:54:33.719548+02:00</CreatedAtDate>
    <IsMileStone>false</IsMileStone>
    <isActive>true</isActive>
    <ScheduledDate xsi:nil="true" />
    <StartDate xsi:nil="true" />
    <RequiredEffortTime xsi:nil="true" />
    <DeadlineDate xsi:nil="true" />
    <CompleteDate xsi:nil="true" />
    <EngineerId xsi:nil="true" />
    <Complexity xsi:nil="true" />
  </Task>
  <Task>
    <Id>12</Id>
    <Alias>workers</Alias>
    <Description>the engineeer need to take control over hirring workers</Description>
    <CreatedAtDate>2023-12-09T19:54:33.7397525+02:00</CreatedAtDate>
    <IsMileStone>false</IsMileStone>
    <isActive>true</isActive>
    <ScheduledDate xsi:nil="true" />
    <StartDate xsi:nil="true" />
    <RequiredEffortTime xsi:nil="true" />
    <DeadlineDate xsi:nil="true" />
    <CompleteDate xsi:nil="true" />
    <EngineerId xsi:nil="true" />
    <Complexity xsi:nil="true" />
  </Task>
  <Task>
    <Id>13</Id>
    <Alias>plaster</Alias>
    <Description>the engineeer need to take control over the plaster of the building</Description>
    <CreatedAtDate>2023-12-22T19:54:33.7876089+02:00</CreatedAtDate>
    <IsMileStone>false</IsMileStone>
    <isActive>true</isActive>
    <ScheduledDate xsi:nil="true" />
    <StartDate xsi:nil="true" />
    <RequiredEffortTime xsi:nil="true" />
    <DeadlineDate xsi:nil="true" />
    <CompleteDate xsi:nil="true" />
    <EngineerId xsi:nil="true" />
    <Complexity xsi:nil="true" />
  </Task>
  <Task>
    <Id>14</Id>
    <Alias>skull</Alias>
    <Description>the engineeer need to take control over the skull of the building</Description>
    <CreatedAtDate>2023-11-15T19:54:33.8047397+02:00</CreatedAtDate>
    <IsMileStone>false</IsMileStone>
    <isActive>true</isActive>
    <ScheduledDate xsi:nil="true" />
    <StartDate xsi:nil="true" />
    <RequiredEffortTime xsi:nil="true" />
    <DeadlineDate xsi:nil="true" />
    <CompleteDate xsi:nil="true" />
    <EngineerId xsi:nil="true" />
    <Complexity xsi:nil="true" />
  </Task>
  <Task>
    <Id>15</Id>
    <Alias>flooring</Alias>
    <Description>the engineeer need to take control over the flooring</Description>
    <CreatedAtDate>2023-11-15T19:54:33.8190782+02:00</CreatedAtDate>
    <IsMileStone>false</IsMileStone>
    <isActive>true</isActive>
    <ScheduledDate xsi:nil="true" />
    <StartDate xsi:nil="true" />
    <RequiredEffortTime xsi:nil="true" />
    <DeadlineDate xsi:nil="true" />
    <CompleteDate xsi:nil="true" />
    <EngineerId xsi:nil="true" />
    <Complexity xsi:nil="true" />
  </Task>
  <Task>
    <Id>16</Id>
    <Alias>windows and door</Alias>
    <Description>the engineeer need to take control over the exits of the building</Description>
    <CreatedAtDate>2023-11-13T19:54:33.8409491+02:00</CreatedAtDate>
    <IsMileStone>false</IsMileStone>
    <isActive>true</isActive>
    <ScheduledDate xsi:nil="true" />
    <StartDate xsi:nil="true" />
    <RequiredEffortTime xsi:nil="true" />
    <DeadlineDate xsi:nil="true" />
    <CompleteDate xsi:nil="true" />
    <EngineerId xsi:nil="true" />
    <Complexity xsi:nil="true" />
  </Task>
  <Task>
    <Id>17</Id>
    <Alias>roof</Alias>
    <Description>the engineeer need to control the roof constraction</Description>
    <CreatedAtDate>2023-11-09T19:54:33.8643371+02:00</CreatedAtDate>
    <IsMileStone>false</IsMileStone>
    <isActive>true</isActive>
    <ScheduledDate xsi:nil="true" />
    <StartDate xsi:nil="true" />
    <RequiredEffortTime xsi:nil="true" />
    <DeadlineDate xsi:nil="true" />
    <CompleteDate xsi:nil="true" />
    <EngineerId xsi:nil="true" />
    <Complexity xsi:nil="true" />
  </Task>
  <Task>
    <Id>18</Id>
    <Alias>Solar panels</Alias>
    <Description>the engineeer need to take control over putting Solar panels</Description>
    <CreatedAtDate>2023-11-04T19:54:33.8806762+02:00</CreatedAtDate>
    <IsMileStone>false</IsMileStone>
    <isActive>true</isActive>
    <ScheduledDate xsi:nil="true" />
    <StartDate xsi:nil="true" />
    <RequiredEffortTime xsi:nil="true" />
    <DeadlineDate xsi:nil="true" />
    <CompleteDate xsi:nil="true" />
    <EngineerId xsi:nil="true" />
    <Complexity xsi:nil="true" />
  </Task>
  <Task>
    <Id>19</Id>
    <Alias>Air-Conditioner</Alias>
    <Description>the engineeer need to take control the Air-Conditioning</Description>
    <CreatedAtDate>2023-11-02T19:54:33.8999447+02:00</CreatedAtDate>
    <IsMileStone>false</IsMileStone>
    <isActive>true</isActive>
    <ScheduledDate xsi:nil="true" />
    <StartDate xsi:nil="true" />
    <RequiredEffortTime xsi:nil="true" />
    <DeadlineDate xsi:nil="true" />
    <CompleteDate xsi:nil="true" />
    <EngineerId xsi:nil="true" />
    <Complexity xsi:nil="true" />
  </Task>
  <Task>
    <Id>20</Id>
    <Alias>rail</Alias>
    <Description>the engineeer need to take control over building the rails in the house</Description>
    <CreatedAtDate>2023-12-13T19:54:33.9148862+02:00</CreatedAtDate>
    <IsMileStone>false</IsMileStone>
    <isActive>true</isActive>
    <ScheduledDate xsi:nil="true" />
    <StartDate xsi:nil="true" />
    <RequiredEffortTime xsi:nil="true" />
    <DeadlineDate xsi:nil="true" />
    <CompleteDate xsi:nil="true" />
    <EngineerId xsi:nil="true" />
    <Complexity xsi:nil="true" />
  </Task>
  <Task>
    <Id>21</Id>
    <Alias>architect</Alias>
    <Description>the engineeer need to take control over the architection</Description>
    <CreatedAtDate>2023-12-27T19:54:33.9316312+02:00</CreatedAtDate>
    <IsMileStone>false</IsMileStone>
    <isActive>true</isActive>
    <ScheduledDate xsi:nil="true" />
    <StartDate xsi:nil="true" />
    <RequiredEffortTime xsi:nil="true" />
    <DeadlineDate xsi:nil="true" />
    <CompleteDate xsi:nil="true" />
    <EngineerId xsi:nil="true" />
    <Complexity xsi:nil="true" />
  </Task>
  <Task>
    <Id>22</Id>
    <Alias>Construction permits</Alias>
    <Description>the engineeer need to take control over the Construction permits</Description>
    <CreatedAtDate>2023-11-22T19:54:33.9530516+02:00</CreatedAtDate>
    <IsMileStone>false</IsMileStone>
    <isActive>true</isActive>
    <ScheduledDate xsi:nil="true" />
    <StartDate xsi:nil="true" />
    <RequiredEffortTime xsi:nil="true" />
    <DeadlineDate xsi:nil="true" />
    <CompleteDate xsi:nil="true" />
    <EngineerId xsi:nil="true" />
    <Complexity xsi:nil="true" />
  </Task>
</ArrayOfTask>